noisocr/__init__.py
noisocr-0.2.dist-info/LICENSE
noisocr-0.2.dist-info/METADATA
noisocr-0.2.dist-info/WHEEL
noisocr-0.2.dist-info/top_level.txt
noisocr-0.2.dist-info/RECORD
