Metadata-Version: 2.1
Name: noisocr
Version: 0.2
Summary: Tools to simulate post-OCR noisy texts.
Author: Sávio Santos
Author-email: savi8sant8s@gmail.com
License: MIT
License-File: LICENSE
Requires-Dist: typo
Requires-Dist: PyHyphen
